checkit/__init__.py
checkit/__main__.py
checkit/bank.py
checkit/dashboard.py
checkit/exercise.py
checkit/outcome.py
checkit/utils.py
checkit/xml.py
checkit/static/README.md
checkit/static/__init__.py
checkit/static/bank.xml
checkit/static/dashboard.ipynb
checkit/static/devcontainer.json
checkit/static/generator.sage
checkit/static/gitignore.txt
checkit/static/html.xsl
checkit/static/latex.xsl
checkit/static/pretext.xsl
checkit/static/setup.sh
checkit/static/template.xml
checkit/static/viewer.zip
checkit/wrapper/__init__.py
checkit/wrapper/wrapper.sage
checkit_dashboard-0.2.7.dist-info/METADATA
checkit_dashboard-0.2.7.dist-info/WHEEL
checkit_dashboard-0.2.7.dist-info/top_level.txt
checkit_dashboard-0.2.7.dist-info/RECORD
