Metadata-Version: 2.4
Name: checkit-dashboard
Version: 0.2.7
Summary: Dashboard for authoring/disseminating randomized exercises
Author: Steven Clontz
Author-email: steven.clontz@gmail.com
License: MIT License
Classifier: Programming Language :: Python :: 3
Classifier: Operating System :: OS Independent
Requires-Python: >=3.8.0
Requires-Dist: ipywidgets
Requires-Dist: lxml
Requires-Dist: latex2mathml
Requires-Dist: pystache
Requires-Dist: trogon
Requires-Dist: click
Provides-Extra: dev
Requires-Dist: build; extra == "dev"
Requires-Dist: twine; extra == "dev"
Requires-Dist: ipykernel; extra == "dev"
Dynamic: requires-dist
